[
  {
    "id": 182785224,
    "name": "Petterson Andrade",
    "photo": "/1/b/c/e/member_280447118.jpeg",
    "going": "no"
  },
  {
    "id": 243922207,
    "name": "Anton Shevchuk",
    "photo": "/b/7/5/f/member_273106943.jpeg",
    "going": "waitlist"
  },
  {
    "id": 277040574,
    "name": "Sanjay Jain",
    "photo": "/7/9/f/9/member_286291225.jpeg",
    "going": "waitlist"
  },
  {
    "id": 279591489,
    "name": "Nadia",
    "photo": "/5/3/1/7/member_289401271.jpeg",
    "going": "waitlist"
  },
  {
    "id": 221215146,
    "name": "Daniel Bock",
    "photo": "/7/0/d/6/member_263908886.jpeg",
    "going": "waitlist"
  },
  {
    "id": 12461312,
    "name": "Dan",
    "photo": "/1/e/d/f/member_11887903.jpeg",
    "going": "waitlist"
  },
  {
    "id": 264069165,
    "name": "Melanie Par",
    "photo": "/3/c/e/2/member_283215586.jpeg",
    "going": "waitlist"
  },
  {
    "id": 292317537,
    "name": "Gloria Caridad Raventós",
    "photo": "/d/d/6/a/member_293036682.jpeg",
    "going": "waitlist"
  },
  {
    "id": 268745283,
    "name": "Ron Cantiveros",
    "photo": "/5/c/0/8/member_283703560.jpeg",
    "going": "waitlist"
  },
  {
    "id": 296241213,
    "name": "Sajjad Heydari",
    "photo": "/2/9/f/c/member_294550748.jpeg",
    "going": "waitlist"
  },
  {
    "id": 182529449,
    "name": "Lucivaldo Costa",
    "photo": "/d/e/8/3/member_241496963.jpeg",
    "going": "waitlist"
  },
  {
    "id": 263004654,
    "name": "Daniel Struthers",
    "photo": "/9/3/6/b/member_280537739.jpeg",
    "going": "waitlist"
  },
  {
    "id": 193465322,
    "name": "Leonardo",
    "photo": "/3/c/f/4/member_250155604.jpeg",
    "going": "waitlist"
  },
  {
    "id": 297916256,
    "name": "Tesfa Demissie",
    "photo": "/8/7/6/1/member_295234657.jpeg",
    "going": "waitlist"
  },
  {
    "id": 227726811,
    "name": "Ryan B.",
    "photo": "",
    "going": "waitlist"
  },
  {
    "id": 197622706,
    "name": "Jayme Desrosiers ",
    "photo": "/8/9/1/4/member_264875092.jpeg",
    "going": "waitlist"
  },
  {
    "id": 263157456,
    "name": "Jay Sachdeva",
    "photo": "/9/2/7/7/member_280597495.jpeg",
    "going": "waitlist"
  },
  {
    "id": 14175524,
    "name": "Dan Bernardic",
    "photo": "/6/1/0/1/member_269184833.jpeg",
    "going": "waitlist"
  },
  {
    "id": 275583382,
    "name": "Alexander Gotfrid",
    "photo": "/d/b/9/d/member_285596221.jpeg",
    "going": "waitlist"
  },
  {
    "id": 264279179,
    "name": "Karan Raj Kohli",
    "photo": "/3/3/5/4/member_281053140.jpeg",
    "going": "waitlist"
  },
  {
    "id": 297797594,
    "name": "Vlad Samonin",
    "photo": "/9/6/7/0/member_295178512.jpeg",
    "going": "waitlist"
  },
  {
    "id": 265775535,
    "name": "Nana",
    "photo": "",
    "going": "waitlist"
  },
  {
    "id": 173301162,
    "name": "Andy Q.",
    "photo": "",
    "going": "no"
  },
  {
    "id": 170270252,
    "name": "Jesse Dyck",
    "photo": "",
    "going": "no"
  },
  {
    "id": 297735487,
    "name": "Anatoliy Furda",
    "photo": "/2/2/a/3/member_295148867.jpeg",
    "going": "yes"
  },
  {
    "id": 297713020,
    "name": "Mario M",
    "photo": "/e/4/a/1/member_295138529.jpeg",
    "going": "yes"
  },
  {
    "id": 217718211,
    "name": "Diego Beltran",
    "photo": "/5/d/9/c/member_290663964.jpeg",
    "going": "yes"
  },
  {
    "id": 246247698,
    "name": "Victor Rengifo",
    "photo": "",
    "going": "yes"
  },
  {
    "id": 237346817,
    "name": "Nico Neiman",
    "photo": "/e/3/d/e/member_270958334.jpeg",
    "going": "yes"
  },
  {
    "id": 260113456,
    "name": "Bruno illipronti",
    "photo": "/7/e/c/2/member_279752450.jpeg",
    "going": "yes"
  },
  {
    "id": 284505586,
    "name": "Priya ",
    "photo": "/e/8/f/c/member_290339644.jpeg",
    "going": "yes"
  },
  {
    "id": 285847636,
    "name": "Юрий Варчук",
    "photo": "/8/0/1/8/member_290672792.jpeg",
    "going": "yes"
  },
  {
    "id": 220784749,
    "name": "Joaquim Neto",
    "photo": "/5/1/5/6/member_263720822.jpeg",
    "going": "yes"
  },
  {
    "id": 37836142,
    "name": "Diogo Villa Verde Bastos",
    "photo": "/b/9/c/b/member_291887563.jpeg",
    "going": "yes"
  },
  {
    "id": 266561494,
    "name": "Roya",
    "photo": "/b/f/5/6/member_287328982.jpeg",
    "going": "yes"
  },
  {
    "id": 275591944,
    "name": "Vruttik Bhatt",
    "photo": "/2/b/6/member_285600694.jpeg",
    "going": "yes"
  },
  {
    "id": 275517713,
    "name": "Arthur Saraiva",
    "photo": "/b/0/7/d/member_292185181.jpeg",
    "going": "yes"
  },
  {
    "id": 248997327,
    "name": "Jagdeep Singh",
    "photo": "/e/6/a/5/member_275039045.jpeg",
    "going": "yes"
  },
  {
    "id": 274833487,
    "name": "Nikita  Tsyganov",
    "photo": "/4/6/7/7/member_285258039.jpeg",
    "going": "yes"
  },
  {
    "id": 215266601,
    "name": "Christie",
    "photo": "/d/e/3/d/member_261176893.jpeg",
    "going": "yes"
  },
  {
    "id": 297639612,
    "name": "Jay Friesen",
    "photo": "/6/0/a/d/member_295104749.jpeg",
    "going": "yes"
  },
  {
    "id": 252134616,
    "name": "Ubeydullah Abdiweli",
    "photo": "/d/4/f/9/member_276654521.jpeg",
    "going": "yes"
  },
  {
    "id": 288604891,
    "name": "Леонид Малановский",
    "photo": "/8/5/7/4/member_291874164.jpeg",
    "going": "yes"
  },
  {
    "id": 258048188,
    "name": "Alexandre Martins",
    "photo": "/b/4/a/1/member_278566241.jpeg",
    "going": "yes"
  },
  {
    "id": 174841422,
    "name": "Junjie Huang",
    "photo": "/a/5/4/8/member_282162312.jpeg",
    "going": "yes"
  },
  {
    "id": 191282144,
    "name": "Adriano Skroch",
    "photo": "/7/d/9/e/member_248792158.jpeg",
    "going": "yes"
  },
  {
    "id": 264519983,
    "name": "xxhelle1986",
    "photo": "",
    "going": "yes"
  },
  {
    "id": 247245842,
    "name": "Paulo Guedes",
    "photo": "/2/e/b/c/member_274331964.jpeg",
    "going": "yes"
  },
  {
    "id": 258822236,
    "name": "Kleyson Prado",
    "photo": "/9/1/8/0/member_278857248.jpeg",
    "going": "yes"
  },
  {
    "id": 242090018,
    "name": "Andre Felipe Scalco",
    "photo": "/a/b/e/7/member_272624007.jpeg",
    "going": "yes"
  },
  {
    "id": 282157015,
    "name": "Renan Caldas",
    "photo": "/5/8/4/4/member_295102596.jpeg",
    "going": "yes"
  },
  {
    "id": 270657743,
    "name": "anh tran",
    "photo": "",
    "going": "yes"
  },
  {
    "id": 262118864,
    "name": "Leonardo Miranda Nunes",
    "photo": "/a/a/a/b/member_280183691.jpeg",
    "going": "yes"
  },
  {
    "id": 262772682,
    "name": "Himanshi Patel",
    "photo": "/1/1/4/d/member_280444429.jpeg",
    "going": "yes"
  },
  {
    "id": 219299426,
    "name": "Viventhraa Rao",
    "photo": "/3/0/0/b/member_282312299.jpeg",
    "going": "yes"
  },
  {
    "id": 213177189,
    "name": "Dmitry Rubin",
    "photo": "/2/9/8/3/member_282610627.jpeg",
    "going": "yes"
  },
  {
    "id": 250449747,
    "name": "yiyi",
    "photo": "/7/6/f/f/member_282630463.jpeg",
    "going": "yes"
  },
  {
    "id": 116173922,
    "name": "Nicolas Isnardi",
    "photo": "/4/f/d/4/member_245540436.jpeg",
    "going": "yes"
  },
  {
    "id": 45785642,
    "name": "Peter Braun",
    "photo": "/d/4/f/a/member_51534522.jpeg",
    "going": "yes"
  }
]
